sc_html2pdf/__init__.py
sc_html2pdf/main.py
sc_html2pdf-0.0.1.dist-info/LICENSE
sc_html2pdf-0.0.1.dist-info/METADATA
sc_html2pdf-0.0.1.dist-info/WHEEL
sc_html2pdf-0.0.1.dist-info/entry_points.txt
sc_html2pdf-0.0.1.dist-info/top_level.txt
sc_html2pdf-0.0.1.dist-info/RECORD
