Metadata-Version: 2.1
Name: sc-html2pdf
Version: 0.0.1
Summary: A simple python project transform html to pdf
Home-page: https://github.com/Scott-Lau/sc-html2pdf
Author: Scott Lau
Author-email: exceedego@126.com
License: MIT
Keywords: python html pdf
Platform: POSIX
Classifier: Programming Language :: Python :: 3
Classifier: Programming Language :: Python :: 3.6
Classifier: Programming Language :: Python :: 3.7
Classifier: Programming Language :: Python :: 3.8
Classifier: Programming Language :: Python :: 3.9
Classifier: License :: OSI Approved :: MIT License
Classifier: Operating System :: OS Independent
Classifier: Topic :: Software Development
Classifier: Topic :: Utilities
Requires-Python: >=3.6
License-File: LICENSE
Requires-Dist: sc-utilities (>=0.0.7)
Requires-Dist: sc-config (>=0.0.11)
Requires-Dist: weasyprint (>=55.0)
